sspeedup/ability/exceptions.py
sspeedup/ability/word_split/_base.py
sspeedup/ability/word_split/jieba.py
sspeedup/api/code.py
sspeedup/api/litestar.py
sspeedup/api/sanic.py
sspeedup/cache/timeout.py
sspeedup/colorful_print.py
sspeedup/config/__init__.py
sspeedup/config/blocks.py
sspeedup/dict_helper.py
sspeedup/feishu/auth.py
sspeedup/feishu/bitable/__init__.py
sspeedup/feishu/bitable/datetime_convert.py
sspeedup/feishu/bitable/structs.py
sspeedup/logging/run_logger.py
sspeedup/make_qrcode.py
sspeedup/pywebio/callbacks.py
sspeedup/pywebio/clipboard.py
sspeedup/pywebio/cookies.py
sspeedup/pywebio/footer.py
sspeedup/pywebio/html.py
sspeedup/pywebio/loading.py
sspeedup/pywebio/navigation.py
sspeedup/pywebio/patch.py
sspeedup/pywebio/query_params.py
sspeedup/pywebio/scope.py
sspeedup/pywebio/toast.py
sspeedup/retry/__init__.py
sspeedup/retry/deco.py
sspeedup/retry/event.py
sspeedup/retry/policy.py
sspeedup/sync_to_async.py
sspeedup/time_helper.py
sspeedup/word_split/_base.py
sspeedup/word_split/jieba.py
sspeedup-0.25.1.dist-info/LICENSE
sspeedup-0.25.1.dist-info/METADATA
sspeedup-0.25.1.dist-info/WHEEL
sspeedup-0.25.1.dist-info/RECORD
