Metadata-Version: 2.1
Name: sspeedup
Version: 0.25.1
Summary: 开发工具箱
Home-page: https://github.com/FHU-yezi/sspeedup
License: MIT
Author: yezi
Author-email: yehaowei20060411@qq.com
Requires-Python: >=3.8,<4.0
Classifier: Development Status :: 4 - Beta
Classifier: License :: OSI Approved :: MIT License
Classifier: Programming Language :: Python :: 3
Classifier: Programming Language :: Python :: 3.8
Classifier: Programming Language :: Python :: 3.9
Classifier: Programming Language :: Python :: 3.10
Classifier: Programming Language :: Python :: 3.11
Classifier: Programming Language :: Python :: 3.12
Classifier: Programming Language :: Python :: 3 :: Only
Classifier: Typing :: Typed
Provides-Extra: ability-word-split
Provides-Extra: api-litestar
Provides-Extra: api-sanic
Provides-Extra: config
Provides-Extra: feishu-auth
Provides-Extra: feishu-bitable
Provides-Extra: pywebio
Provides-Extra: qrcode
Provides-Extra: word-split-jieba
Requires-Dist: httpx (==0.*) ; extra == "feishu-auth" or extra == "feishu-bitable" or extra == "ability-word-split"
Requires-Dist: jieba (>=0.42.0,<0.43.0) ; extra == "word-split-jieba"
Requires-Dist: litestar (>=2.3.0,<3.0.0) ; extra == "api-litestar"
Requires-Dist: motor (>=3.3.0,<4.0.0)
Requires-Dist: msgspec (==0.*) ; extra == "config" or extra == "feishu-bitable" or extra == "api-litestar"
Requires-Dist: pydantic (>=2.0.0,<3.0.0) ; extra == "api-sanic"
Requires-Dist: pymongo (>=4.3.0,<5.0.0)
Requires-Dist: pywebio (>=1.8.0,<2.0.0) ; extra == "pywebio"
Requires-Dist: qrcode (>=7.4.0,<8.0.0) ; extra == "qrcode"
Requires-Dist: sanic (>=23.3.0,<24.0.0) ; extra == "api-sanic"
Requires-Dist: ujson (>=5.8.0,<6.0.0) ; extra == "api-sanic"
Project-URL: Repository, https://github.com/FHU-yezi/sspeedup
